vynil/__init__.py
vynil/__main__.py
vynil/api.py
vynil/assets/__init__.py
vynil/assets/asset.py
vynil/assets/font.py
vynil/assets/image.py
vynil/assets/script.py
vynil/assets/style.py
vynil/book.py
vynil/cli.py
vynil/components/__init__.py
vynil/components/builtins/admonition.html.aur
vynil/components/builtins/columns.html.aur
vynil/components/builtins/dinkus.html.aur
vynil/components/builtins/image.html.aur
vynil/components/builtins/item.html.aur
vynil/components/builtins/list.html.aur
vynil/components/builtins/page.html.aur
vynil/components/builtins/table.html.aur
vynil/components/component.py
vynil/components/inline.py
vynil/components/plugins/__init__.py
vynil/components/plugins/chapter.py
vynil/components/plugins/vynil.py
vynil/formats/__init__.py
vynil/formats/common.css
vynil/formats/ebook/__init__.py
vynil/formats/ebook/ebook.css
vynil/formats/ebook/ebook.html
vynil/formats/ebook/ebook.py
vynil/formats/ebook/ebook_display.html
vynil/formats/ebook/epub.min.js
vynil/formats/ebook/jszip.min.js
vynil/formats/format.py
vynil/formats/print/__init__.py
vynil/formats/print/paged.interface.css
vynil/formats/print/paged.polyfill.min.js
vynil/formats/print/print.css
vynil/formats/print/print.html.aur
vynil/formats/print/print.py
vynil/formats/render.py
vynil/formats/server.py
vynil/formats/syntax-highlighting.css
vynil/formats/web/__init__.py
vynil/formats/web/web.css
vynil/formats/web/web.html.aur
vynil/formats/web/web.js
vynil/formats/web/web.py
vynil/py.typed
vynil-0.1.3.dist-info/METADATA
vynil-0.1.3.dist-info/WHEEL
vynil-0.1.3.dist-info/entry_points.txt
vynil-0.1.3.dist-info/RECORD
