Metadata-Version: 2.3
Name: vynil
Version: 0.1.3
Summary: The Vynil Book Generation Framework
Author: Dan Gittik
Author-email: dan.gittik@gmail.com
Requires-Python: >=3.12
Classifier: Programming Language :: Python :: 3
Classifier: Programming Language :: Python :: 3.12
Classifier: Programming Language :: Python :: 3.13
Requires-Dist: auryn (>=1.0.2)
Requires-Dist: ebooklib (>=0.19,<0.20)
Requires-Dist: fonttools (>=4.57.0,<5.0.0)
Requires-Dist: latex2mathml (>=3.78.0,<4.0.0)
Requires-Dist: playwright (>=1.52.0,<2.0.0)
Requires-Dist: pydantic (>=2.11.4,<3.0.0)
Requires-Dist: pygments (>=2.19.1,<3.0.0)
Requires-Dist: pyyaml (>=6.0.2,<7.0.0)
Requires-Dist: watchdog (>=6.0.0,<7.0.0)
